LICENSE
README.md
setup.py
fast_boltzmann.egg-info/PKG-INFO
fast_boltzmann.egg-info/SOURCES.txt
fast_boltzmann.egg-info/dependency_links.txt
fast_boltzmann.egg-info/requires.txt
fast_boltzmann.egg-info/top_level.txt
src/fast_boltzmann/__init__.py
src/fast_boltzmann/fast_boltzmann.py
src/fast_boltzmann/utils.py