Metadata-Version: 2.1
Name: fast-boltzmann
Version: 1.0.0
Summary: `fast_boltzmann` is a Python package developed for the fast computation of the Boltzmann Entropy (also known as configurational entropy) for a two-dimensional numerical or nominal data array.
Home-page: https://github.com/geoye/fast_boltzmann
Author: Yuxuan YE<yuxuanye145@gmail.com>, Xinghua Cheng<cxh9791156936@gmail.com>
Author-email: yuxuanye145@gmail.com, cxh9791156936@gmail.com
License: MIT
Project-URL: Source, https://github.com/geoye/fast_boltzmann
Project-URL: Bug Tracker, https://github.com/geoye/fast_boltzmann/issues
Keywords: python,entropy,quality assessment,thermodynamic consistency,landscape ecology
Classifier: Operating System :: OS Independent
Classifier: License :: OSI Approved :: MIT License
Classifier: Programming Language :: Python
Classifier: Topic :: Scientific/Engineering :: Image Processing
Classifier: Topic :: Scientific/Engineering :: Information Analysis
Classifier: Topic :: Software Development :: Libraries :: Python Modules
Requires-Python: >=3.6
License-File: LICENSE
